MANIFEST.in
setup.cfg
setup.py
cevsubmit/__init__.py
cevsubmit/__main__.py
cevsubmit.egg-info/PKG-INFO
cevsubmit.egg-info/SOURCES.txt
cevsubmit.egg-info/dependency_links.txt
cevsubmit.egg-info/entry_points.txt
cevsubmit.egg-info/requires.txt
cevsubmit.egg-info/top_level.txt
cevsubmit/locale/es/LC_MESSAGES/cevsubmit.po