Metadata-Version: 1.2
Name: cevsubmit
Version: 0.0.4
Summary: This is cevsubmit, with which you can submit solutions to cev's private repositories github.
Home-page: https://github.com/cutting-edge-visionaries/cevsubmit
Author: Ujjwal (CEVian)
Author-email: contact@cevgroup.org
License: GPLv3
Keywords: submit,cevsubmit
Platform: UNKNOWN
Classifier: Intended Audience :: Education
Classifier: Programming Language :: Python :: 3
Classifier: Topic :: Education
Classifier: Topic :: Utilities
Requires-Python: >=3.6
